aind_mgi_service_async_client/__init__.py
aind_mgi_service_async_client/api_client.py
aind_mgi_service_async_client/api_response.py
aind_mgi_service_async_client/configuration.py
aind_mgi_service_async_client/exceptions.py
aind_mgi_service_async_client/py.typed
aind_mgi_service_async_client/rest.py
aind_mgi_service_async_client/api/__init__.py
aind_mgi_service_async_client/api/default_api.py
aind_mgi_service_async_client/api/healthcheck_api.py
aind_mgi_service_async_client/models/__init__.py
aind_mgi_service_async_client/models/health_check.py
aind_mgi_service_async_client/models/http_validation_error.py
aind_mgi_service_async_client/models/mgi_summary_row.py
aind_mgi_service_async_client/models/validation_error.py
aind_mgi_service_async_client/models/validation_error_loc_inner.py
aind_mgi_service_async_client-0.1.2.dist-info/METADATA
aind_mgi_service_async_client-0.1.2.dist-info/WHEEL
aind_mgi_service_async_client-0.1.2.dist-info/top_level.txt
aind_mgi_service_async_client-0.1.2.dist-info/RECORD
